serversock/__init__.py
serversock/serversock.py
serversock-0.1.dist-info/LICENSE
serversock-0.1.dist-info/METADATA
serversock-0.1.dist-info/WHEEL
serversock-0.1.dist-info/entry_points.txt
serversock-0.1.dist-info/top_level.txt
serversock-0.1.dist-info/RECORD
