Metadata-Version: 2.1
Name: serversock
Version: 0.1
Summary: create multi-client server using multi-threading
Author-email: Soumyo Deep Gupta <deep.main.ac@gmail.com>
Maintainer-email: Soumyo Deep Gupta <deep.main.ac@gmail.com>
License: MIT License
Project-URL: GitHub, https://github.com/d33pster/serversock
Project-URL: Issues, https://github.com/d33pster/serversock/issues
Project-URL: Documentation, https://d33pster.github.io/serversock/
Keywords: d33pster,serversock,socket-server,socket,multiclient,server,multiple-client
Classifier: Development Status :: 4 - Beta
Classifier: Intended Audience :: Developers
Classifier: Topic :: Software Development :: Build Tools
Classifier: Programming Language :: Python :: 3.9
Classifier: Programming Language :: Python :: 3.10
Classifier: Programming Language :: Python :: 3.11
Classifier: Programming Language :: Python :: 3.12
Classifier: License :: OSI Approved :: MIT License
Classifier: Operating System :: OS Independent
Requires-Python: >=3.9
License-File: LICENSE
Requires-Dist: optioner >=1.4.2
Requires-Dist: colorama
